ppcore/__init__.py
ppcore/proxy.py
ppcore/proxy_pool.py
ppcore/request.py
ppcore/validator.py
ppcore/api/__init__.py
ppcore/api/api.py
proxy_pool_core-0.0.1.dev1.dist-info/DESCRIPTION.rst
proxy_pool_core-0.0.1.dev1.dist-info/METADATA
proxy_pool_core-0.0.1.dev1.dist-info/RECORD
proxy_pool_core-0.0.1.dev1.dist-info/WHEEL
proxy_pool_core-0.0.1.dev1.dist-info/metadata.json
proxy_pool_core-0.0.1.dev1.dist-info/top_level.txt
