Metadata-Version: 2.0
Name: proxy-pool-core
Version: 0.0.1.dev1
Summary: A Proxy Pool Project.
Home-page: UNKNOWN
Author: Sean Xu
Author-email: xuqingjian8@gmail.com
License: UNKNOWN
Keywords: proxy proxypool validate tornado
Platform: UNKNOWN
Requires-Dist: tornado
